LICENSE
MANIFEST.in
README.rst
setup.cfg
setup.py
versioneer.py
artellapipe/__init__.py
artellapipe/tools/__init__.py
artellapipe/tools/lightrigsmanager/__init__.py
artellapipe/tools/lightrigsmanager/__logging__.ini
artellapipe/tools/lightrigsmanager/__version__.py
artellapipe/tools/lightrigsmanager/_version.py
artellapipe/tools/lightrigsmanager/core/__init__.py
artellapipe/tools/lightrigsmanager/core/api.py
artellapipe/tools/lightrigsmanager/core/lightrigsmanager.py
artellapipe/tools/lightrigsmanager/resources/icons/lightrigs/default.png
artellapipe/tools/lightrigsmanager/resources/images/lightrigsmanager_logo.png
artellapipe/tools/lightrigsmanager/resources/images/no_light_rigs.png
artellapipe/tools/lightrigsmanager/widgets/__init__.py
artellapipe/tools/lightrigsmanager/widgets/lightrigsmanager.py
artellapipe_tools_lightrigsmanager.egg-info/PKG-INFO
artellapipe_tools_lightrigsmanager.egg-info/SOURCES.txt
artellapipe_tools_lightrigsmanager.egg-info/dependency_links.txt
artellapipe_tools_lightrigsmanager.egg-info/not-zip-safe
artellapipe_tools_lightrigsmanager.egg-info/requires.txt
artellapipe_tools_lightrigsmanager.egg-info/top_level.txt
tests/__init__.py
tests/test_general.py