Metadata-Version: 2.1
Name: artellapipe-tools-lightrigsmanager
Version: 0.0.9
Summary: Tool to easily import light rigs into DCC scenes
Home-page: https://github.com/ArtellaPipe/artellapipe-tools-lightrigsmanager
Author: Tomas Poveda
Author-email: tpovedatd@gmail.com
License: MIT
Platform: UNKNOWN
Provides-Extra: test
Provides-Extra: dev
